public final class com/dylibso/chicory/$gen/CompiledModule {

  private <init>()V
    ALOAD 0
    INVOKESPECIAL java/lang/Object.<init> ()V
    RETURN

  public static func_0(IIIILcom/dylibso/chicory/runtime/Memory;Lcom/dylibso/chicory/runtime/Instance;)I
    ALOAD 5
    ICONST_0
    ICONST_4
    NEWARRAY T_LONG
    DUP
    ICONST_0
    ILOAD 0
    I2L
    LASTORE
    DUP
    ICONST_1
    ILOAD 1
    I2L
    LASTORE
    DUP
    ICONST_2
    ILOAD 2
    I2L
    LASTORE
    DUP
    ICONST_3
    ILOAD 3
    I2L
    LASTORE
    INVOKEVIRTUAL com/dylibso/chicory/runtime/Instance.callHostFunction (I[J)[J
    ICONST_0
    LALOAD
    L2I
    IRETURN

  public static func_1(Lcom/dylibso/chicory/runtime/Memory;Lcom/dylibso/chicory/runtime/Instance;)V
    ICONST_0
    BIPUSH 8
    ICONST_0
    ALOAD 0
    INVOKESTATIC com/dylibso/chicory/aot/runtime/AotMethods.memoryWriteInt (IIILcom/dylibso/chicory/runtime/Memory;)V
    ICONST_4
    BIPUSH 12
    ICONST_0
    ALOAD 0
    INVOKESTATIC com/dylibso/chicory/aot/runtime/AotMethods.memoryWriteInt (IIILcom/dylibso/chicory/runtime/Memory;)V
    ICONST_1
    ICONST_0
    ICONST_1
    BIPUSH 20
    INVOKESTATIC com/dylibso/chicory/aot/runtime/AotMethods.checkInterruption ()V
    ALOAD 0
    ALOAD 1
    INVOKESTATIC com/dylibso/chicory/$gen/CompiledModule.func_0 (IIIILcom/dylibso/chicory/runtime/Memory;Lcom/dylibso/chicory/runtime/Instance;)I
    POP
    RETURN

  public static call_indirect_0(IIIIIILcom/dylibso/chicory/runtime/Memory;Lcom/dylibso/chicory/runtime/Instance;)I
    INVOKESTATIC com/dylibso/chicory/aot/runtime/AotMethods.checkInterruption ()V
    ALOAD 7
    ILOAD 5
    INVOKEVIRTUAL com/dylibso/chicory/runtime/Instance.table (I)Lcom/dylibso/chicory/runtime/TableInstance;
    ASTORE 8
    ALOAD 8
    ILOAD 4
    INVOKESTATIC com/dylibso/chicory/aot/runtime/AotMethods.tableRef (Lcom/dylibso/chicory/runtime/TableInstance;I)I
    ISTORE 9
    ALOAD 8
    ILOAD 4
    INVOKEVIRTUAL com/dylibso/chicory/runtime/TableInstance.instance (I)Lcom/dylibso/chicory/runtime/Instance;
    ASTORE 10
    ALOAD 10
    IFNULL L0
    ALOAD 10
    ALOAD 7
    IF_ACMPNE L1
   L0
    ILOAD 0
    ILOAD 1
    ILOAD 2
    ILOAD 3
    ALOAD 6
    ALOAD 7
    ILOAD 9
    LOOKUPSWITCH
      0: L2
      default: L3
   L2
    INVOKESTATIC com/dylibso/chicory/$gen/CompiledModule.func_0 (IIIILcom/dylibso/chicory/runtime/Memory;Lcom/dylibso/chicory/runtime/Instance;)I
    IRETURN
   L3
    INVOKESTATIC com/dylibso/chicory/aot/runtime/AotMethods.throwIndirectCallTypeMismatch ()Ljava/lang/RuntimeException;
    ATHROW
   L1
    ICONST_4
    NEWARRAY T_LONG
    DUP
    ICONST_0
    ILOAD 0
    I2L
    LASTORE
    DUP
    ICONST_1
    ILOAD 1
    I2L
    LASTORE
    DUP
    ICONST_2
    ILOAD 2
    I2L
    LASTORE
    DUP
    ICONST_3
    ILOAD 3
    I2L
    LASTORE
    ICONST_0
    ILOAD 9
    ALOAD 10
    INVOKESTATIC com/dylibso/chicory/aot/runtime/AotMethods.callIndirect ([JIILcom/dylibso/chicory/runtime/Instance;)[J
    ICONST_0
    LALOAD
    L2I
    IRETURN

  public static call_indirect_1(IILcom/dylibso/chicory/runtime/Memory;Lcom/dylibso/chicory/runtime/Instance;)V
    INVOKESTATIC com/dylibso/chicory/aot/runtime/AotMethods.checkInterruption ()V
    ALOAD 3
    ILOAD 1
    INVOKEVIRTUAL com/dylibso/chicory/runtime/Instance.table (I)Lcom/dylibso/chicory/runtime/TableInstance;
    ASTORE 4
    ALOAD 4
    ILOAD 0
    INVOKESTATIC com/dylibso/chicory/aot/runtime/AotMethods.tableRef (Lcom/dylibso/chicory/runtime/TableInstance;I)I
    ISTORE 5
    ALOAD 4
    ILOAD 0
    INVOKEVIRTUAL com/dylibso/chicory/runtime/TableInstance.instance (I)Lcom/dylibso/chicory/runtime/Instance;
    ASTORE 6
    ALOAD 6
    IFNULL L0
    ALOAD 6
    ALOAD 3
    IF_ACMPNE L1
   L0
    ALOAD 2
    ALOAD 3
    ILOAD 5
    LOOKUPSWITCH
      1: L2
      default: L3
   L2
    INVOKESTATIC com/dylibso/chicory/$gen/CompiledModule.func_1 (Lcom/dylibso/chicory/runtime/Memory;Lcom/dylibso/chicory/runtime/Instance;)V
    RETURN
   L3
    INVOKESTATIC com/dylibso/chicory/aot/runtime/AotMethods.throwIndirectCallTypeMismatch ()Ljava/lang/RuntimeException;
    ATHROW
   L1
    ICONST_0
    NEWARRAY T_LONG
    ICONST_1
    ILOAD 5
    ALOAD 6
    INVOKESTATIC com/dylibso/chicory/aot/runtime/AotMethods.callIndirect ([JIILcom/dylibso/chicory/runtime/Instance;)[J
    RETURN
}
