// class version 55.0 (55)
// access flags 0x11
public final class FOO {

  // compiled from: wasm
  // debug info: wasm

  // access flags 0x2
  private <init>()V
    ALOAD 0
    INVOKESPECIAL java/lang/Object.<init> ()V
    RETURN
    MAXSTACK = 1
    MAXLOCALS = 1

  // access flags 0x9
  public static func_0(Lcom/dylibso/chicory/runtime/Memory;Lcom/dylibso/chicory/runtime/Instance;)V
    LDC -2147483648
    POP
    ICONST_0
    POP
    LDC 2147483647
    POP
    LDC -9223372036854775808
    POP2
    LCONST_0
    POP2
    LDC 9223372036854775807
    POP2
    LDC -2147483647
    POP
    LDC 2147483646
    POP
    LDC -9223372036854775807
    POP2
    LDC 9223372036854775806
    POP2
    ICONST_M1
    POP
    ICONST_1
    POP
    LDC -1
    POP2
    LCONST_1
    POP2
    RETURN
    MAXSTACK = 2
    MAXLOCALS = 2

  // access flags 0x9
  public static call_indirect_0(IILcom/dylibso/chicory/runtime/Memory;Lcom/dylibso/chicory/runtime/Instance;)V
    INVOKESTATIC com/dylibso/chicory/aot/runtime/AotMethods.checkInterruption ()V
    ALOAD 3
    ILOAD 1
    INVOKEVIRTUAL com/dylibso/chicory/runtime/Instance.table (I)Lcom/dylibso/chicory/runtime/TableInstance;
    ASTORE 4
    ALOAD 4
    ILOAD 0
    INVOKESTATIC com/dylibso/chicory/aot/runtime/AotMethods.tableRef (Lcom/dylibso/chicory/runtime/TableInstance;I)I
    ISTORE 5
    ALOAD 4
    ILOAD 0
    INVOKEVIRTUAL com/dylibso/chicory/runtime/TableInstance.instance (I)Lcom/dylibso/chicory/runtime/Instance;
    ASTORE 6
    ALOAD 6
    IFNULL L0
    ALOAD 6
    ALOAD 3
    IF_ACMPNE L1
   L0
   FRAME APPEND [com/dylibso/chicory/runtime/TableInstance I com/dylibso/chicory/runtime/Instance]
    ALOAD 2
    ALOAD 3
    ILOAD 5
    LOOKUPSWITCH
      0: L2
      default: L3
   L2
   FRAME FULL [I I com/dylibso/chicory/runtime/Memory com/dylibso/chicory/runtime/Instance com/dylibso/chicory/runtime/TableInstance I com/dylibso/chicory/runtime/Instance] [com/dylibso/chicory/runtime/Memory com/dylibso/chicory/runtime/Instance]
    INVOKESTATIC FOO.func_0 (Lcom/dylibso/chicory/runtime/Memory;Lcom/dylibso/chicory/runtime/Instance;)V
    GOTO L4
   L3
   FRAME FULL [I I com/dylibso/chicory/runtime/Memory com/dylibso/chicory/runtime/Instance com/dylibso/chicory/runtime/TableInstance I com/dylibso/chicory/runtime/Instance] [com/dylibso/chicory/runtime/Memory com/dylibso/chicory/runtime/Instance]
    INVOKESTATIC com/dylibso/chicory/aot/runtime/AotMethods.throwIndirectCallTypeMismatch ()Ljava/lang/RuntimeException;
    ATHROW
   L4
   FRAME SAME
    RETURN
   L1
   FRAME SAME
    ICONST_0
    NEWARRAY T_LONG
    ICONST_0
    ILOAD 5
    ALOAD 6
    INVOKESTATIC com/dylibso/chicory/aot/runtime/AotMethods.callIndirect ([JIILcom/dylibso/chicory/runtime/Instance;)[J
    RETURN
    MAXSTACK = 4
    MAXLOCALS = 7
}
