public final class com/dylibso/chicory/$gen/CompiledMachine implements com/dylibso/chicory/runtime/Machine {

  private final Lcom/dylibso/chicory/runtime/Instance; instance

  public <init>(Lcom/dylibso/chicory/runtime/Instance;)V
    ALOAD 0
    INVOKESPECIAL java/lang/Object.<init> ()V
    ALOAD 0
    ALOAD 1
    PUTFIELD com/dylibso/chicory/$gen/CompiledMachine.instance : Lcom/dylibso/chicory/runtime/Instance;
    RETURN

  public call(I[J)[J
    TRYCATCHBLOCK L0 L1 L1 java/lang/StackOverflowError
   L0
    ALOAD 0
    GETFIELD com/dylibso/chicory/$gen/CompiledMachine.instance : Lcom/dylibso/chicory/runtime/Instance;
    DUP
    INVOKEVIRTUAL com/dylibso/chicory/runtime/Instance.memory ()Lcom/dylibso/chicory/runtime/Memory;
    ILOAD 1
    ALOAD 2
    INVOKESTATIC com/dylibso/chicory/$gen/CompiledMachineMachineCall.call (Lcom/dylibso/chicory/runtime/Instance;Lcom/dylibso/chicory/runtime/Memory;I[J)[J
    ARETURN
   L1
    INVOKESTATIC com/dylibso/chicory/$gen/CompiledMachineShaded.throwCallStackExhausted (Ljava/lang/StackOverflowError;)Ljava/lang/RuntimeException;
    ATHROW

  public static call_indirect_0(IIIILcom/dylibso/chicory/runtime/Memory;Lcom/dylibso/chicory/runtime/Instance;)I
    INVOKESTATIC com/dylibso/chicory/$gen/CompiledMachineShaded.checkInterruption ()V
    ALOAD 5
    ILOAD 3
    INVOKEVIRTUAL com/dylibso/chicory/runtime/Instance.table (I)Lcom/dylibso/chicory/runtime/TableInstance;
    ASTORE 6
    ALOAD 6
    ILOAD 2
    INVOKEVIRTUAL com/dylibso/chicory/runtime/TableInstance.requiredRef (I)I
    ISTORE 7
    ALOAD 6
    ILOAD 2
    INVOKEVIRTUAL com/dylibso/chicory/runtime/TableInstance.instance (I)Lcom/dylibso/chicory/runtime/Instance;
    ASTORE 8
    ALOAD 8
    IFNULL L0
    ALOAD 8
    ALOAD 5
    IF_ACMPNE L1
   L0
    ILOAD 0
    ILOAD 1
    ALOAD 4
    ALOAD 5
    ILOAD 7
    LOOKUPSWITCH
      0: L2
      default: L3
   L2
    INVOKESTATIC com/dylibso/chicory/$gen/CompiledMachineFuncGroup_0.func_0 (IILcom/dylibso/chicory/runtime/Memory;Lcom/dylibso/chicory/runtime/Instance;)I
    IRETURN
   L3
    INVOKESTATIC com/dylibso/chicory/$gen/CompiledMachineShaded.throwIndirectCallTypeMismatch ()Ljava/lang/RuntimeException;
    ATHROW
   L1
    ICONST_2
    NEWARRAY T_LONG
    DUP
    ICONST_0
    ILOAD 0
    I2L
    LASTORE
    DUP
    ICONST_1
    ILOAD 1
    I2L
    LASTORE
    ICONST_0
    ILOAD 7
    ALOAD 8
    INVOKESTATIC com/dylibso/chicory/$gen/CompiledMachineShaded.callIndirect ([JIILcom/dylibso/chicory/runtime/Instance;)[J
    ICONST_0
    LALOAD
    L2I
    IRETURN

  public static call_indirect_1([JIILcom/dylibso/chicory/runtime/Memory;Lcom/dylibso/chicory/runtime/Instance;)I
    INVOKESTATIC com/dylibso/chicory/$gen/CompiledMachineShaded.checkInterruption ()V
    ALOAD 4
    ILOAD 2
    INVOKEVIRTUAL com/dylibso/chicory/runtime/Instance.table (I)Lcom/dylibso/chicory/runtime/TableInstance;
    ASTORE 5
    ALOAD 5
    ILOAD 1
    INVOKEVIRTUAL com/dylibso/chicory/runtime/TableInstance.requiredRef (I)I
    ISTORE 6
    ALOAD 5
    ILOAD 1
    INVOKEVIRTUAL com/dylibso/chicory/runtime/TableInstance.instance (I)Lcom/dylibso/chicory/runtime/Instance;
    ASTORE 7
    ALOAD 7
    IFNULL L0
    ALOAD 7
    ALOAD 4
    IF_ACMPNE L1
   L0
    ALOAD 0
    ALOAD 3
    ALOAD 4
    ILOAD 6
    LOOKUPSWITCH
      1: L2
      default: L3
   L2
    INVOKESTATIC com/dylibso/chicory/$gen/CompiledMachineFuncGroup_0.func_1 ([JLcom/dylibso/chicory/runtime/Memory;Lcom/dylibso/chicory/runtime/Instance;)I
    IRETURN
   L3
    INVOKESTATIC com/dylibso/chicory/$gen/CompiledMachineShaded.throwIndirectCallTypeMismatch ()Ljava/lang/RuntimeException;
    ATHROW
   L1
    ALOAD 0
    ICONST_1
    ILOAD 6
    ALOAD 7
    INVOKESTATIC com/dylibso/chicory/$gen/CompiledMachineShaded.callIndirect ([JIILcom/dylibso/chicory/runtime/Instance;)[J
    ICONST_0
    LALOAD
    L2I
    IRETURN
}

final class com/dylibso/chicory/$gen/CompiledMachineFuncGroup_0 {

  public static func_0(IILcom/dylibso/chicory/runtime/Memory;Lcom/dylibso/chicory/runtime/Instance;)I
    ILOAD 0
    LCONST_0
    FCONST_0
    DCONST_0
    ICONST_M1
    ICONST_M1
#foreach ($const in $iconst)
    ICONST_0
#end
    ILOAD 1
    INVOKESTATIC com/dylibso/chicory/$gen/CompiledMachineShaded.checkInterruption ()V
#foreach ($store in $istore)
    #set($store = 305 - $store)
    ISTORE $store
#end
    DSTORE 8
    FSTORE 7
    LSTORE 5
    ISTORE 4
    SIPUSH 300
    NEWARRAY T_LONG
    DUP
    ICONST_0
    ILOAD 4
    I2L
    LASTORE
    DUP
    ICONST_1
    LLOAD 5
    LASTORE
    DUP
    ICONST_2
    FLOAD 7
    INVOKESTATIC com/dylibso/chicory/wasm/types/Value.floatToLong (F)J
    LASTORE
    DUP
    ICONST_3
    DLOAD 8
    INVOKESTATIC com/dylibso/chicory/wasm/types/Value.doubleToLong (D)J
    LASTORE
    DUP
    ICONST_4
    ILOAD 10
    I2L
    LASTORE
    DUP
    ICONST_5
    ILOAD 11
    I2L
    LASTORE
#foreach ($splat in $splats1)
    #set($const = $splat)
    #set($load = $splat + 6)
    DUP
    BIPUSH $const
    ILOAD $load
    I2L
    LASTORE
#end
#foreach ($splat in $splats2)
    #set($const = $splat)
    #set($load = $splat + 6)
    DUP
    SIPUSH $const
    ILOAD $load
    I2L
    LASTORE
#end
    ALOAD 2
    ALOAD 3
    INVOKESTATIC com/dylibso/chicory/$gen/CompiledMachineFuncGroup_0.func_1 ([JLcom/dylibso/chicory/runtime/Memory;Lcom/dylibso/chicory/runtime/Instance;)I
    IRETURN

  public static call_0(Lcom/dylibso/chicory/runtime/Instance;Lcom/dylibso/chicory/runtime/Memory;[J)[J
    ALOAD 2
    ICONST_0
    LALOAD
    L2I
    ALOAD 2
    ICONST_1
    LALOAD
    L2I
    ALOAD 1
    ALOAD 0
    INVOKESTATIC com/dylibso/chicory/$gen/CompiledMachineFuncGroup_0.func_0 (IILcom/dylibso/chicory/runtime/Memory;Lcom/dylibso/chicory/runtime/Instance;)I
    I2L
    LSTORE 3
    ICONST_1
    NEWARRAY T_LONG
    DUP
    ICONST_0
    LLOAD 3
    LASTORE
    ARETURN

  public static func_1([JLcom/dylibso/chicory/runtime/Memory;Lcom/dylibso/chicory/runtime/Instance;)I
    ALOAD 0
    ICONST_0
    LALOAD
    L2I
    ISTORE 3
    ALOAD 0
    ICONST_1
    LALOAD
    LSTORE 4
    ALOAD 0
    ICONST_2
    LALOAD
    INVOKESTATIC com/dylibso/chicory/wasm/types/Value.longToFloat (J)F
    FSTORE 6
    ALOAD 0
    ICONST_3
    LALOAD
    INVOKESTATIC com/dylibso/chicory/wasm/types/Value.longToDouble (J)D
    DSTORE 7
    ALOAD 0
    ICONST_4
    LALOAD
    L2I
    ISTORE 9
    ALOAD 0
    ICONST_5
#foreach ($splat in $splats3)
    #set($bipush = $splat)
    #set($store = $splat + 4)
    LALOAD
    L2I
    ISTORE $store
    ALOAD 0
    BIPUSH $bipush
#end
#foreach ($splat in $splats4)
    #set($bipush = $splat)
    #set($store = $splat + 4)
    LALOAD
    L2I
    ISTORE $store
    ALOAD 0
    SIPUSH $bipush
#end
    LALOAD
    L2I
    ISTORE 304
    ILOAD 3
    ILOAD 304
    IADD
    IRETURN

  public static call_1(Lcom/dylibso/chicory/runtime/Instance;Lcom/dylibso/chicory/runtime/Memory;[J)[J
    ALOAD 2
    ALOAD 1
    ALOAD 0
    INVOKESTATIC com/dylibso/chicory/$gen/CompiledMachineFuncGroup_0.func_1 ([JLcom/dylibso/chicory/runtime/Memory;Lcom/dylibso/chicory/runtime/Instance;)I
    I2L
    LSTORE 3
    ICONST_1
    NEWARRAY T_LONG
    DUP
    ICONST_0
    LLOAD 3
    LASTORE
    ARETURN
}

final class com/dylibso/chicory/$gen/CompiledMachineMachineCall {

  public <init>()V
    ALOAD 0
    INVOKESPECIAL java/lang/Object.<init> ()V
    RETURN

  public static call(Lcom/dylibso/chicory/runtime/Instance;Lcom/dylibso/chicory/runtime/Memory;I[J)[J
    ALOAD 0
    ALOAD 1
    ALOAD 3
    ILOAD 2
    TABLESWITCH
      0: L0
      1: L1
      default: L2
   L0
    INVOKESTATIC com/dylibso/chicory/$gen/CompiledMachineFuncGroup_0.call_0 (Lcom/dylibso/chicory/runtime/Instance;Lcom/dylibso/chicory/runtime/Memory;[J)[J
    ARETURN
   L1
    INVOKESTATIC com/dylibso/chicory/$gen/CompiledMachineFuncGroup_0.call_1 (Lcom/dylibso/chicory/runtime/Instance;Lcom/dylibso/chicory/runtime/Memory;[J)[J
    ARETURN
   L2
    ILOAD 2
    INVOKESTATIC com/dylibso/chicory/$gen/CompiledMachineShaded.throwUnknownFunction (I)Ljava/lang/RuntimeException;
    ATHROW
}
